EssaySummarizer.py
EssaySummarizer-0.0.2.dist-info/LICENSE
EssaySummarizer-0.0.2.dist-info/METADATA
EssaySummarizer-0.0.2.dist-info/WHEEL
EssaySummarizer-0.0.2.dist-info/top_level.txt
EssaySummarizer-0.0.2.dist-info/RECORD
