Metadata-Version: 2.1
Name: EssaySummarizer
Version: 0.0.2
Summary: Essay Summarizer.
Home-page: UNKNOWN
Author: Ujjwal Reddy K S
License: UNKNOWN
Keywords: Essay,Summarizer,nltk
Platform: UNKNOWN
Classifier: Programming Language :: Python :: 3
Classifier: License :: OSI Approved :: MIT License
Classifier: Operating System :: OS Independent
Requires-Python: >=3.6
License-File: LICENSE
Requires-Dist: nltk
